LICENSE.txt
MANIFEST.in
README.md
setup.cfg
setup.py
moult/__init__.py
moult/__main__.py
moult/args.py
moult/ast_scanner.py
moult/classes.py
moult/color.py
moult/compat.py
moult/exceptions.py
moult/filesystem_scanner.py
moult/log.py
moult/pip_importer.py
moult/printer.py
moult/program.py
moult/utils.py
moult.egg-info/PKG-INFO
moult.egg-info/SOURCES.txt
moult.egg-info/dependency_links.txt
moult.egg-info/entry_points.txt
moult.egg-info/top_level.txt
moult/frameworks/__init__.py
moult/frameworks/django.py