Metadata-Version: 1.1
Name: moult
Version: 0.1.2
Summary: A utility for finding Python packages that may not be in use.
Home-page: https://github.com/tweekmonster/moult
Author: Tommy Allen
Author-email: tommy@esdf.io
License: MIT
Keywords: uninstall remove packages development environment requirements
Platform: UNKNOWN
Classifier: Development Status :: 4 - Beta
Classifier: Intended Audience :: Developers
Classifier: License :: OSI Approved :: MIT License
Classifier: Programming Language :: Python :: 2
Classifier: Programming Language :: Python :: 2.7
Classifier: Programming Language :: Python :: 3
Classifier: Programming Language :: Python :: 3.2
Classifier: Programming Language :: Python :: 3.3
Classifier: Programming Language :: Python :: 3.4
Classifier: Programming Language :: Python :: Implementation :: PyPy
